odoo8_addon_account_bank_statement_import_coda-8.0.1.0.0.99.dev14-py2.7-nspkg.pth
odoo8_addon_account_bank_statement_import_coda-8.0.1.0.0.99.dev14.dist-info/DESCRIPTION.rst
odoo8_addon_account_bank_statement_import_coda-8.0.1.0.0.99.dev14.dist-info/METADATA
odoo8_addon_account_bank_statement_import_coda-8.0.1.0.0.99.dev14.dist-info/RECORD
odoo8_addon_account_bank_statement_import_coda-8.0.1.0.0.99.dev14.dist-info/WHEEL
odoo8_addon_account_bank_statement_import_coda-8.0.1.0.0.99.dev14.dist-info/metadata.json
odoo8_addon_account_bank_statement_import_coda-8.0.1.0.0.99.dev14.dist-info/namespace_packages.txt
odoo8_addon_account_bank_statement_import_coda-8.0.1.0.0.99.dev14.dist-info/top_level.txt
odoo_addons/account_bank_statement_import_coda/README.rst
odoo_addons/account_bank_statement_import_coda/__init__.py
odoo_addons/account_bank_statement_import_coda/__openerp__.py
odoo_addons/account_bank_statement_import_coda/i18n/account_bank_statement_import_coda.pot
odoo_addons/account_bank_statement_import_coda/i18n/ca_ES.po
odoo_addons/account_bank_statement_import_coda/i18n/de.po
odoo_addons/account_bank_statement_import_coda/i18n/fi.po
odoo_addons/account_bank_statement_import_coda/i18n/fr.po
odoo_addons/account_bank_statement_import_coda/i18n/nl_NL.po
odoo_addons/account_bank_statement_import_coda/static/description/icon.png
odoo_addons/account_bank_statement_import_coda/test_coda_file/Ontvangen_CODA.2012-01-11-18.59.15.txt
odoo_addons/account_bank_statement_import_coda/tests/__init__.py
odoo_addons/account_bank_statement_import_coda/tests/test_import_bank_statement.py
odoo_addons/account_bank_statement_import_coda/views/account_bank_statement_view.xml
odoo_addons/account_bank_statement_import_coda/wizard/__init__.py
odoo_addons/account_bank_statement_import_coda/wizard/account_bank_statement_import_coda.py
